pynitors/__init__.py
pynitors/main.py
pynitors/py.typed
pynitors-0.1.0.dist-info/WHEEL
pynitors-0.1.0.dist-info/entry_points.txt
pynitors-0.1.0.dist-info/METADATA
pynitors-0.1.0.dist-info/RECORD
