Metadata-Version: 2.3
Name: pynitors
Version: 0.1.0
Summary: CLI System monitor build in python.
Author: ariefminardi
Author-email: ariefminardi <ariefminardi140@gmail.com>
Requires-Dist: psutil>=7.0.0
Requires-Dist: typer>=0.17.4
Requires-Python: >=3.12
